TongguoCeshiXuexiGoBianchengFix1/README.md
TongguoCeshiXuexiGoBianchengFix1/__init__.py
TongguoCeshiXuexiGoBianchengFix1/__main__.py
TongguoCeshiXuexiGoBianchengFix1/file.epub
TongguoCeshiXuexiGoBianchengFix1/index.html
TongguoCeshiXuexiGoBianchengFix1/css/__init__.py
TongguoCeshiXuexiGoBianchengFix1/css/annotations.css
TongguoCeshiXuexiGoBianchengFix1/css/main.css
TongguoCeshiXuexiGoBianchengFix1/css/normalize.css
TongguoCeshiXuexiGoBianchengFix1/css/popup.css
TongguoCeshiXuexiGoBianchengFix1/font/__init__.py
TongguoCeshiXuexiGoBianchengFix1/font/fontello.eot
TongguoCeshiXuexiGoBianchengFix1/font/fontello.svg
TongguoCeshiXuexiGoBianchengFix1/font/fontello.ttf
TongguoCeshiXuexiGoBianchengFix1/font/fontello.woff
TongguoCeshiXuexiGoBianchengFix1/img/__init__.py
TongguoCeshiXuexiGoBianchengFix1/img/annotator-glyph-sprite.png
TongguoCeshiXuexiGoBianchengFix1/img/annotator-icon-sprite.png
TongguoCeshiXuexiGoBianchengFix1/img/apple-touch-icon.png
TongguoCeshiXuexiGoBianchengFix1/img/cancelfullscreen.png
TongguoCeshiXuexiGoBianchengFix1/img/close.png
TongguoCeshiXuexiGoBianchengFix1/img/fullscreen.png
TongguoCeshiXuexiGoBianchengFix1/img/loader.gif
TongguoCeshiXuexiGoBianchengFix1/img/menu-icon.png
TongguoCeshiXuexiGoBianchengFix1/img/save.png
TongguoCeshiXuexiGoBianchengFix1/img/saved.png
TongguoCeshiXuexiGoBianchengFix1/img/settings-s.png
TongguoCeshiXuexiGoBianchengFix1/img/settings.png
TongguoCeshiXuexiGoBianchengFix1/img/star.png
TongguoCeshiXuexiGoBianchengFix1/js/__init__.py
TongguoCeshiXuexiGoBianchengFix1/js/epub.js
TongguoCeshiXuexiGoBianchengFix1/js/epub.min.js
TongguoCeshiXuexiGoBianchengFix1/js/epub.min.map
TongguoCeshiXuexiGoBianchengFix1/js/hooks.min.js
TongguoCeshiXuexiGoBianchengFix1/js/hooks.min.map
TongguoCeshiXuexiGoBianchengFix1/js/reader.js
TongguoCeshiXuexiGoBianchengFix1/js/reader.js.map
TongguoCeshiXuexiGoBianchengFix1/js/reader.min.js
TongguoCeshiXuexiGoBianchengFix1/js/reader.min.map
TongguoCeshiXuexiGoBianchengFix1/js/hooks/__init__.py
tongguo_ceshi_xuexi_go_biancheng_fix1-2025.3.25.0.dist-info/METADATA
tongguo_ceshi_xuexi_go_biancheng_fix1-2025.3.25.0.dist-info/WHEEL
tongguo_ceshi_xuexi_go_biancheng_fix1-2025.3.25.0.dist-info/entry_points.txt
tongguo_ceshi_xuexi_go_biancheng_fix1-2025.3.25.0.dist-info/top_level.txt
tongguo_ceshi_xuexi_go_biancheng_fix1-2025.3.25.0.dist-info/RECORD
